{
  "schemaVersion": 1,
  "id": "item-compare",
  "version": "${version}",
  "name": "Item Compare",
  "description": "A professional item comparison tool for Hypixel Skyblock. Compare stats, enchantments, and item differences side-by-side with visual +/- indicators.",
  "authors": [
    "kr3mil"
  ],
  "contact": {
    "homepage": "https://github.com/kr3mil/item-compare",
    "sources": "https://github.com/kr3mil/item-compare"
  },
  "license": "MIT",
  "icon": "assets/item-compare/icon.png",
  "environment": "*",
  "entrypoints": {
    "main": [
      "com.itemcompare.ItemCompare"
    ],
    "client": [
      "com.itemcompare.ItemCompareClient"
    ]
  },
  "mixins": [
    "item-compare.mixins.json"
  ],
  "depends": {
    "fabricloader": ">=0.16.14",
    "minecraft": "~1.21.5",
    "java": ">=21",
    "fabric-api": "*"
  },
  "suggests": {}
}